sphinxcontrib/specs/__init__.py
sphinxcontrib/specs/admonitions/__init__.py
sphinxcontrib/specs/builder.py
sphinxcontrib/specs/content.py
sphinxcontrib/specs/objectives.py
sphinxcontrib/specs/overridenodes.py
sphinxcontrib/specs/steps.py
sphinxcontrib/specs/theme/layout.html
sphinxcontrib/specs/theme/page.html
sphinxcontrib/specs/theme/static/components.css
sphinxcontrib/specs/theme/static/content.css
sphinxcontrib/specs/theme/static/layout.css
sphinxcontrib/specs/theme/static/styles.css
sphinxcontrib/specs/theme/theme.conf
sphinxcontrib_specs-2.0.2.dist-info/LICENSE
sphinxcontrib_specs-2.0.2.dist-info/METADATA
sphinxcontrib_specs-2.0.2.dist-info/WHEEL
sphinxcontrib_specs-2.0.2.dist-info/RECORD
