Metadata-Version: 2.1
Name: sphinxcontrib-specs
Version: 2.0.2
Summary: Extensions for building Specializations content.
License: MPL-2.0
Author: Ashley Trinh
Author-email: ashley@hackbrightacademy.com
Requires-Python: >=3.9,<4.0
Classifier: License :: OSI Approved
Classifier: Programming Language :: Python :: 3
Classifier: Programming Language :: Python :: 3.9
Classifier: Programming Language :: Python :: 3.10
Classifier: Programming Language :: Python :: 3.11
